flashboot_core/__init__.py
flashboot_core/env/__init__.py
flashboot_core/env/environment.py
flashboot_core/env/properties_property_source_loader.py
flashboot_core/env/property_source.py
flashboot_core/env/property_source_loader.py
flashboot_core/env/yaml_property_source_loader.py
flashboot_core/io/__init__.py
flashboot_core/io/file.py
flashboot_core/io/file_system_resource.py
flashboot_core/io/resource.py
flashboot_core/utils/__init__.py
py_flashboot_core-0.1.1.dist-info/METADATA
py_flashboot_core-0.1.1.dist-info/WHEEL
py_flashboot_core-0.1.1.dist-info/top_level.txt
py_flashboot_core-0.1.1.dist-info/RECORD
