Metadata-Version: 2.4
Name: py-flashboot-core
Version: 0.1.1
Summary: Add your description here
Requires-Python: >=3.10
Requires-Dist: commons-lang>=0.2.1
Requires-Dist: loguru>=0.7.3
Requires-Dist: pyyaml>=6.0.2
